[
  {
    "fiId": "0001",
    "fdDate": "12/10/2016",
    "fiUserId": "0001",
    "fsCustomerId": "11111111111",
    "fiSource":  "2",
    "fsApplicationId": "SD_APP",
    "fsAppVersion": "1.0.0",
    "fsDeviceId": "9e0137c160...",
    "fsDeviceModel": "SM-T533",
    "fsDeviceOS": "Android 5.1.1",
    "fsProblem": "Se indico una notifica come letta poi la ritrovo da leggere",
    "fsAnswer": "La informiamo che il problema \u00e8 stato risolto",
    "fsContact": "pippo",
    "fsMail": "pippo@axiossd.it",
    "fsPhone": "3402574767",
    "fiStatus": "2",
    "fiRefId": "",
    "fiUserSatisfaction": "1",
    "fsUserComment": "Non era proprio quello che volevo ma funziona"
  },
  {
    "fiId": "0003",
    "fdDate": "12/10/2016",
    "fiUserId": "0001",
    "fsCustomerId": "11111111111",
    "fiSource":  "2",
    "fsApplicationId": "SD_APP",
    "fsAppVersion": "1.0.0",
    "fsDeviceId": "9e0137c160...",
    "fsDeviceModel": "SM-T533",
    "fsDeviceOS": "Android 5.1.1",
    "fsProblem": "Gentili dirigenti Axios, in che modo potrei liberarmi di quelle due pippe di Rocchi Stefano e De Vita Daniele? Grazie in anticipo.",
    "fsAnswer": "Gentile Cliente, purtroppo ci facciamo la stessa domanda da anni, senza successo.",
    "fsContact": "pippo",
    "fsMail": "pippo@axiossd.it",
    "fsPhone": "3402574767",
    "fiStatus": "2",
    "fiRefId":  "",
    "fiUserSatisfaction": "5",
    "fsUserComment": "Buono buono"
  },
  {
    "fiId": "0002",
    "fdDate": "12/10/2016",
    "fiUserId": "0001",
    "fsCustomerId": "11111111111",
    "fiSource":  "2",
    "fsApplicationId": "SD_APP",
    "fsAppVersion": "1.0.0",
    "fsDeviceId": "9e0137c160...",
    "fsDeviceModel": "SM-T533",
    "fsDeviceOS": "Android 5.1.1",
    "fsProblem": "Se voglio rispondere ad una mail non mi pare la pagina",
    "fsAnswer": "",
    "fsContact": "pippo",
    "fsMail": "pippo@axiossd.it",
    "fsPhone": "3402574767",
    "fiStatus": "0",
    "fiRefId": "",
    "fiUserSatisfaction": "0",
    "fsUserComment": ""
  },
  {
    "fiId": "0004",
    "fdDate": "12/10/2016",
    "fiUserId": "0001",
    "fsCustomerId": "11111111111",
    "fiSource":  "2",
    "fsApplicationId": "SD_APP",
    "fsAppVersion": "1.0.0",
    "fsDeviceId": "9e0137c160...",
    "fsDeviceModel": "SM-T533",
    "fsDeviceOS": "Android 5.1.1",
    "fsProblem": "Trovate il modo per piacere... magari con il gas... :-)",
    "fsAnswer": "",
    "fsContact": "pippo",
    "fsMail": "pippo@axiossd.it",
    "fsPhone": "3402574767",
    "fiStatus": "0",
    "fiRefId": "0003",
    "fiUserSatisfaction": "0",
    "fsUserComment": ""
  },
  {
    "fiId": "0005",
    "fdDate": "12/10/2016",
    "fiUserId": "0001",
    "fsCustomerId": "11111111111",
    "fiSource":  "2",
    "fsApplicationId": "SD_APP",
    "fsAppVersion": "1.0.0",
    "fsDeviceId": "9e0137c160...",
    "fsDeviceModel": "SM-T533",
    "fsDeviceOS": "Android 5.1.1",
    "fsProblem": "Gli eventi sul calendario scompaiono",
    "fsAnswer": "",
    "fsContact": "pippo",
    "fsMail": "pippo@axiossd.it",
    "fsPhone": "3402574767",
    "fiStatus": "1",
    "fiRefId": "",
    "fiUserSatisfaction": "0",
    "fsUserComment": ""
  }
]